urlopen2/__init__.py
urlopen2/aurlfile.py
urlopen2/aurlfile.pyi
urlopen2/types.py
urlopen2/urlfile.py
urlopen2/urlfile.pyi
urlopen2-1.4.0.dist-info/LICENSE
urlopen2-1.4.0.dist-info/METADATA
urlopen2-1.4.0.dist-info/WHEEL
urlopen2-1.4.0.dist-info/RECORD
