Metadata-Version: 2.1
Name: urlopen2
Version: 1.4.0
Summary: Improvement for the `urllib.request.urlopen` function.
License: MIT
Keywords: urlopen,urllib.request,urlfile,readable,seekable
Author: Romanin
Author-email: semina054@gmail.com
Requires-Python: >=3.7,<3.12
Classifier: License :: OSI Approved :: MIT License
Classifier: Programming Language :: Python :: 3
Classifier: Programming Language :: Python :: 3.7
Classifier: Programming Language :: Python :: 3.8
Classifier: Programming Language :: Python :: 3.9
Classifier: Programming Language :: Python :: 3.10
Classifier: Programming Language :: Python :: 3.11
Requires-Dist: aiofiles (>=23)
Requires-Dist: asyncio (>=3.4)
